{"query":{"namespaces":{"-2":{"id":-2,"case":"first-letter","*":"M\u00e9di\u00e1","canonical":"Media"},"-1":{"id":-1,"case":"first-letter","*":"\u0160peci\u00e1lne","canonical":"Special"},"0":{"id":0,"case":"first-letter","*":"","content":""},"1":{"id":1,"case":"first-letter","*":"Diskusia","subpages":"","canonical":"Talk"},"2":{"id":2,"case":"first-letter","*":"Redaktor","subpages":"","canonical":"User"},"3":{"id":3,"case":"first-letter","*":"Diskusia s redaktorom","subpages":"","canonical":"User talk"},"4":{"id":4,"case":"first-letter","*":"Wikip\u00e9dia","subpages":"","canonical":"Project"},"5":{"id":5,"case":"first-letter","*":"Diskusia k Wikip\u00e9dii","subpages":"","canonical":"Project talk"},"6":{"id":6,"case":"first-letter","*":"S\u00fabor","canonical":"File"},"7":{"id":7,"case":"first-letter","*":"Diskusia k s\u00faboru","subpages":"","canonical":"File talk"},"8":{"id":8,"case":"first-letter","*":"MediaWiki","canonical":"MediaWiki"},"9":{"id":9,"case":"first-letter","*":"Diskusia k MediaWiki","subpages":"","canonical":"MediaWiki talk"},"10":{"id":10,"case":"first-letter","*":"\u0160abl\u00f3na","subpages":"","canonical":"Template"},"11":{"id":11,"case":"first-letter","*":"Diskusia k \u0161abl\u00f3ne","subpages":"","canonical":"Template talk"},"12":{"id":12,"case":"first-letter","*":"Pomoc","subpages":"","canonical":"Help"},"13":{"id":13,"case":"first-letter","*":"Diskusia k pomoci","subpages":"","canonical":"Help talk"},"14":{"id":14,"case":"first-letter","*":"Kateg\u00f3ria","canonical":"Category"},"15":{"id":15,"case":"first-letter","*":"Diskusia ku kateg\u00f3rii","subpages":"","canonical":"Category talk"},"100":{"id":100,"case":"first-letter","*":"Port\u00e1l","subpages":"","canonical":"Port\u00e1l"},"101":{"id":101,"case":"first-letter","*":"Diskusia k port\u00e1lu","subpages":"","canonical":"Diskusia k port\u00e1lu"}},"namespacealiases":[{"id":6,"*":"Image"},{"id":7,"*":"Image talk"},{"id":1,"*":"Koment\u00e1r"},{"id":3,"*":"Koment\u00e1r k redaktorovi"},{"id":6,"*":"Obr\u00e1zok"},{"id":7,"*":"Diskusia k obr\u00e1zku"},{"id":7,"*":"Koment\u00e1r k obr\u00e1zku"},{"id":9,"*":"Koment\u00e1r k MediaWiki"},{"id":5,"*":"Koment\u00e1r k Wikip\u00e9dii"}]}}